plsdbmcp/__init__.py
plsdbmcp/main.py
plsdb_mcp-0.1.0.dist-info/METADATA
plsdb_mcp-0.1.0.dist-info/WHEEL
plsdb_mcp-0.1.0.dist-info/entry_points.txt
plsdb_mcp-0.1.0.dist-info/top_level.txt
plsdb_mcp-0.1.0.dist-info/RECORD
