Metadata-Version: 2.4
Name: plsdb-mcp
Version: 0.1.0
Summary: Model Context Protocol server for interacting with the PLSDB (Plasmid Database) API
Author: PLSDB MCP Team
Author-email: MCPmed Contributors <matthias.flotho@ccb.uni-saarland.de>
License: MIT
Project-URL: Homepage, https://github.com/matthiasflo/PLSDBmcp
Project-URL: Repository, https://github.com/matthiasflo/PLSDBmcp
Project-URL: Issues, https://github.com/matthiasflo/PLSDBmcp/issues
Classifier: Development Status :: 4 - Beta
Classifier: Intended Audience :: Developers
Classifier: License :: OSI Approved :: MIT License
Classifier: Programming Language :: Python :: 3
Classifier: Programming Language :: Python :: 3.8
Classifier: Programming Language :: Python :: 3.9
Classifier: Programming Language :: Python :: 3.10
Classifier: Programming Language :: Python :: 3.11
Classifier: Programming Language :: Python :: 3.12
Requires-Python: >=3.8
Requires-Dist: mcp>=1.0.0
Requires-Dist: aiohttp>=3.8.0
Dynamic: author
Dynamic: requires-python
